inc/__init__.py
inc/__main__.py
inc/app.py
inc/config.py
inc/run.py
inc/bash/conda_python311.sh
inc/bash/conda_python312.sh
inc/bash/dotfiles.sh
inc/bash/gmsh.sh
inc/bash/hello.sh
inc-0.1.7.dist-info/entry_points.txt
inc-0.1.7.dist-info/licenses/LICENSE
inc-0.1.7.dist-info/WHEEL
inc-0.1.7.dist-info/METADATA
inc-0.1.7.dist-info/RECORD
