Metadata-Version: 2.4
Name: inc
Version: 0.1.7
Summary: install new computer
Keywords: python
Author-email: joamatab <4514346+joamatab@users.noreply.github.com>
Requires-Python: >=3.6
Classifier: Programming Language :: Python :: 3.10
Classifier: Programming Language :: Python :: 3.11
Classifier: Operating System :: OS Independent
License-File: LICENSE
Requires-Dist: typer
Requires-Dist: pre-commit ; extra == "dev"
Requires-Dist: pytest ; extra == "dev"
Requires-Dist: pytest-cov ; extra == "dev"
Requires-Dist: pytest_regressions ; extra == "dev"
Requires-Dist: autodoc_pydantic ; extra == "docs"
Requires-Dist: jupyter-book>=0.15.1,<1.1 ; extra == "docs"
Requires-Dist: tbump ; extra == "maintainer"
Requires-Dist: towncrier ; extra == "maintainer"
Requires-Dist: ruff ; extra == "maintainer"
Provides-Extra: dev
Provides-Extra: docs
Provides-Extra: maintainer
